LICENSE
README.md
setup.py
shutil_extra/__init__.py
shutil_extra/dirtree.py
shutil_extra.egg-info/PKG-INFO
shutil_extra.egg-info/SOURCES.txt
shutil_extra.egg-info/dependency_links.txt
shutil_extra.egg-info/top_level.txt