Metadata-Version: 2.1
Name: shutil-extra
Version: 0.0.6
Summary: A successful sign for python setup
Home-page: https://github.com/novawei/shutil_extra
Author: novawei
Author-email: 913252732@qq.com
License: MIT Licence
Keywords: pip,shutil extra,dir tree
Platform: any
License-File: LICENSE
